xupeng/__init__.py
xupeng/aaa.py
xupeng-0.0.2.dist-info/WHEEL
xupeng-0.0.2.dist-info/METADATA
xupeng-0.0.2.dist-info/RECORD
