Metadata-Version: 2.1
Name: xupeng
Version: 0.0.2
Summary: 许鹏的第一个包
Author-email: 许鹏 <1311192345@qq.com>
Requires-Dist: tornado
Requires-Dist: requests
